symbol_counter/__init__.py
symbol_counter/__main__.py
symbol_counter/cli.py
symbol_counter/core.py
symbol_counter-0.1.0.dist-info/licenses/LICENSE
symbol_counter-0.1.0.dist-info/METADATA
symbol_counter-0.1.0.dist-info/WHEEL
symbol_counter-0.1.0.dist-info/entry_points.txt
symbol_counter-0.1.0.dist-info/top_level.txt
symbol_counter-0.1.0.dist-info/RECORD
