Metadata-Version: 2.4
Name: symbol-counter
Version: 0.1.0
Summary: Count unique symbols in a string or file.
Author-email: YOUR_NAME <you@example.com>
License: MIT License
Keywords: text,counter,cli
Classifier: Programming Language :: Python :: 3
Classifier: License :: OSI Approved :: MIT License
Requires-Python: >=3.9
License-File: LICENSE
Dynamic: license-file
